ftrotta/pycolib/__init__.py
ftrotta/pycolib/_amodule.py
ftrotta/pycolib/common_tests.py
ftrotta/pycolib/input_checks.py
ftrotta/pycolib/log.py
ftrotta/pycolib/setup.py
ftrotta.pycolib-1.2.4.dist-info/LICENSE
ftrotta.pycolib-1.2.4.dist-info/METADATA
ftrotta.pycolib-1.2.4.dist-info/WHEEL
ftrotta.pycolib-1.2.4.dist-info/top_level.txt
ftrotta.pycolib-1.2.4.dist-info/RECORD
