Metadata-Version: 2.1
Name: ftrotta.pycolib
Version: 1.2.4
Summary: A collection of tools of common usage in Python
Home-page: UNKNOWN
Author: Francesco Trotta
License: UNKNOWN
Project-URL: Source Code, https://gitlab.com/ftrotta/pycolib
Project-URL: Documentation, https://ftrotta-pycolib.readthedocs.io
Platform: UNKNOWN
Classifier: License :: OSI Approved :: GNU General Public License v3 (GPLv3)
Classifier: Operating System :: OS Independent
Classifier: Programming Language :: Python :: 3
Requires-Python: >=3.6
Requires-Dist: attrs (<22,>=20.3.0)
Requires-Dist: numpy (<2,>=1.19.5)
Requires-Dist: deprecated (<2,>=1.2.13)
